LICENSE
MANIFEST.in
README.md
setup.py
lib_curso_python_pro_avellar.egg-info/PKG-INFO
lib_curso_python_pro_avellar.egg-info/SOURCES.txt
lib_curso_python_pro_avellar.egg-info/dependency_links.txt
lib_curso_python_pro_avellar.egg-info/not-zip-safe
lib_curso_python_pro_avellar.egg-info/requires.txt
lib_curso_python_pro_avellar.egg-info/top_level.txt
libpythonpro/__init__.py
libpythonpro/github_api.py
libpythonpro/spam/__init__.py
libpythonpro/spam/db.py
libpythonpro/spam/enviador_de_email.py
libpythonpro/spam/main.py
libpythonpro/spam/modelos.py
libpythonpro/tests/__init__.py
libpythonpro/tests/test_exemplo.py
libpythonpro/tests/test_spam/__init__.py
libpythonpro/tests/test_spam/conftest.py
libpythonpro/tests/test_spam/test_enviador_de_email.py
libpythonpro/tests/test_spam/test_envio_para_base_de_usuarios.py
libpythonpro/tests/test_spam/test_github_api.py
libpythonpro/tests/test_spam/test_usuarios.py