Metadata-Version: 2.1
Name: lib-curso-python-pro-avellar
Version: 0.2
Summary: Módulo para exemplificar construção de projetos Python no
Home-page: https://github.com/avellar1975/libpythonpro
Author: Evandro Avellar
Author-email: evandro.avellar@gmail.com
License: GNU Affero General Public License v3 or later (AGPLv3+)
Platform: UNKNOWN
Classifier: Development Status :: 2 - Pre-Alpha
Classifier: Environment :: Console
Classifier: Intended Audience :: Developers
Classifier: License :: OSI Approved :: GNU Affero General Public License v3 or later (AGPLv3+)
Classifier: Operating System :: OS Independent
Classifier: Programming Language :: Python
Classifier: Programming Language :: Python :: 3.8
Classifier: Framework :: Pytest
